[{"EnrollementID":1,"Prescriptions": [ {"PHARMACY_name":"PHARMACY_1" },{"no_of_tablets":2} ,{"tablet_name":"chrocine","no_of_days":3 } ],"Status":true,"RemindMe":true,"Ordered":false,"PharmacyID":{"$oid":"61de6790fc13ae3c73000460"},"total_amount":"$5.62","Mobile_number":"+56 185 505 8117"},
{"EnrollementID":2,"Prescriptions":  [ { "PHARMACY_name":"PHARMACY_TYPES_2"     },{"no_of_tablets":2} ,{"tablet_name":"chrocine","no_of_days":3 } ],"Status":false,"RemindMe":false,"Ordered":false,"PharmacyID":{"$oid":"61de6790fc13ae3c73000461"},"total_amount":"$9.38","Mobile_number":"+62 579 348 2622"},
{"EnrollementID":3,"Prescriptions":  [ { "PHARMACY_name":"PHARMACY_TYPES_3"    },{"no_of_tablets":2} ,{"tablet_name":"chrocine","no_of_days":3 } ],"Status":true,"RemindMe":true,"Ordered":true,"PharmacyID":{"$oid":"61de6790fc13ae3c73000462"},"total_amount":"$7.84","Mobile_number":"+62 349 302 0465"},
{"EnrollementID":4,"Prescriptions":  [ { "PHARMACY_name":"PHARMACY_TYPES_4"    },{"no_of_tablets":2} ,{"tablet_name":"chrocine","no_of_days":3 } ],"Status":true,"RemindMe":false,"Ordered":false,"PharmacyID":{"$oid":"61de6790fc13ae3c73000463"},"total_amount":"$7.60","Mobile_number":"+86 861 317 7050"},
{"EnrollementID":5,"Prescriptions":  [ { "PHARMACY_name":"PHARMACY_TYPES_5"     },{"no_of_tablets":2} ,{"tablet_name":"chrocine","no_of_days":3 } ],"Status":true,"RemindMe":true,"Ordered":true,"PharmacyID":{"$oid":"61de6790fc13ae3c73000464"},"total_amount":"$6.06","Mobile_number":"+62 390 830 1376"},
{"EnrollementID":6,"Prescriptions":  [ { "PHARMACY_name":"PHARMACY_TYPES_6"     },{"no_of_tablets":2} ,{"tablet_name":"chrocine","no_of_days":3 } ],"Status":true,"RemindMe":true,"Ordered":false,"PharmacyID":{"$oid":"61de6790fc13ae3c73000465"},"total_amount":"$9.58","Mobile_number":"+86 470 941 9634"},
{"EnrollementID":7,"Prescriptions":  [ { "PHARMACY_name":"PHARMACY_TYPES_7"   },{"no_of_tablets":2} ,{"tablet_name":"chrocine","no_of_days":3 } ],"Status":true,"RemindMe":true,"Ordered":false,"PharmacyID":{"$oid":"61de6790fc13ae3c73000466"},"total_amount":"$5.69","Mobile_number":"+1 907 109 3378"},
{"EnrollementID":8,"Prescriptions":  [ { "PHARMACY_name":"PHARMACY_TYPES_8"     },{"no_of_tablets":2} ,{"tablet_name":"chrocine","no_of_days":3 } ],"Status":false,"RemindMe":false,"Ordered":true,"PharmacyID":{"$oid":"61de6790fc13ae3c73000467"},"total_amount":"$8.98","Mobile_number":"+57 168 180 6880"},
{"EnrollementID":9,"Prescriptions":  [ { "PHARMACY_name":"PHARMACY_TYPES_9"     },{"no_of_tablets":2} ,{"tablet_name":"chrocine","no_of_days":3 } ],"Status":false,"RemindMe":true,"Ordered":false,"PharmacyID":{"$oid":"61de6790fc13ae3c73000468"},"total_amount":"$8.41","Mobile_number":"+386 776 716 3127"},
{"EnrollementID":10,"Prescriptions": [ {"PHARMACY_name":"PHARMACY_TYPES_10"    },{"no_of_tablets":2} ,{"tablet_name":"chrocine","no_of_days":3 } ],"Status":false,"RemindMe":true,"Ordered":true,"PharmacyID":{"$oid":"61de6790fc13ae3c73000469"},"total_amount":"$7.59","Mobile_number":"9542994236"}]